MANIFEST.in
README.md
setup.py
docs/xi_covutils/aux.m.html
docs/xi_covutils/clustering.m.html
docs/xi_covutils/distances.m.html
docs/xi_covutils/index.html
docs/xi_covutils/msa.m.html
docs/xi_covutils/pdbmapper.m.html
docs/xi_covutils/read_results.m.html
docs/xi_covutils/roc.m.html
docs/xi_covutils/smooth.m.html
xi_covutils/__init__.py
xi_covutils/aux_func.c
xi_covutils/clustering.py
xi_covutils/distances.py
xi_covutils/msa.py
xi_covutils/pdbmapper.py
xi_covutils/read_results.py
xi_covutils/roc.py
xi_covutils/smooth.py
xi_covutils.egg-info/PKG-INFO
xi_covutils.egg-info/SOURCES.txt
xi_covutils.egg-info/dependency_links.txt
xi_covutils.egg-info/not-zip-safe
xi_covutils.egg-info/requires.txt
xi_covutils.egg-info/top_level.txt