Metadata-Version: 1.0
Name: xi-covutils
Version: 0.2.0
Summary: Tools to work with protein covariation
Home-page: https://gitlab.com/bioinformatics-fil/xi_covutils
Author: Javier Iserte
Author-email: jiserte@leloir.org.ar
License: I dont know yet
Platform: UNKNOWN
